fraud/__init__.py
fraud/core/__init__.py
fraud/core/api.py
fraud/core/base.py
fraud/core/utils.py
fraud/plugins/__init__.py
fraud/plugins/faker.py
fraud/plugins/gliner.py
fraud/utils/__init__.py
fraud/utils/_decorators.py
fraud-0.1.2.dist-info/METADATA
fraud-0.1.2.dist-info/WHEEL
fraud-0.1.2.dist-info/top_level.txt
fraud-0.1.2.dist-info/RECORD
