Metadata-Version: 2.2
Name: fraud
Version: 0.1.2
Summary: Simple Synthetic Data with Python
Project-URL: Homepage, https://github.com/TrevorW-code/fraud
Classifier: Programming Language :: Python :: 3
Classifier: License :: OSI Approved :: MIT License
Classifier: Operating System :: OS Independent
Requires-Python: >=3.12
Requires-Dist: faker==33.1.0
Requires-Dist: pytest==8.3.4
Requires-Dist: gliner==0.2.13
